{"cameraMode":{"drawMode":0,"name":"Shaded","section":"Shading Mode"},"sceneLighting":true,"audioPlay":false,"sceneViewState":{"m_AlwaysRefresh":false,"showFog":true,"showSkybox":true,"showFlares":true,"showImageEffects":true,"showParticleSystems":true,"showVisualEffectGraphs":true,"m_FxEnabled":true},"in2DMode":false,"pivot":{"x":0.9162535667419434,"y":-1.5222045183181763,"z":-0.9477404356002808},"rotation":{"x":0.08893118053674698,"y":0.9013552665710449,"z":-0.36105796694755556,"w":0.22201019525527955},"size":6.308621883392334,"orthographic":false}